setup.py
bin/pakrat
pakrat/__init__.py
pakrat/log.py
pakrat/progress.py
pakrat/repo.py
pakrat/repos.py
pakrat/util.py
pakrat/yumbase.py
pakrat.egg-info/PKG-INFO
pakrat.egg-info/SOURCES.txt
pakrat.egg-info/dependency_links.txt
pakrat.egg-info/top_level.txt