Metadata-Version: 1.0
Name: pakrat
Version: 0.3.1
Summary: A Python library for mirroring and versioning YUM repositories
Home-page: https://github.com/ryanuber/pakrat
Author: Ryan Uber
Author-email: ru@ryanuber.com
License: UNKNOWN
Platform: UNKNOWN
